Ocrversion1/__init__.py
Ocrversion1/main.py
Ocrversion2-0.2.0.dist-info/METADATA
Ocrversion2-0.2.0.dist-info/WHEEL
Ocrversion2-0.2.0.dist-info/top_level.txt
Ocrversion2-0.2.0.dist-info/RECORD
