Metadata-Version: 2.1
Name: Ocrversion2
Version: 0.2.0
Requires-Dist: annotated-types (==0.6.0)
Requires-Dist: anyio (==3.7.1)
Requires-Dist: certifi (==2022.12.7)
Requires-Dist: cffi (==1.16.0)
Requires-Dist: charset-normalizer (==2.1.1)
Requires-Dist: click (==8.1.7)
Requires-Dist: colorama (==0.4.6)
Requires-Dist: contourpy (==1.2.0)
Requires-Dist: cryptography (==41.0.7)
Requires-Dist: cycler (==0.12.1)
Requires-Dist: easyocr (==1.7.1)
Requires-Dist: fastapi (==0.104.1)
Requires-Dist: filelock (==3.9.0)
Requires-Dist: fonttools (==4.46.0)
Requires-Dist: fsspec (==2023.4.0)
Requires-Dist: h11 (==0.14.0)
Requires-Dist: idna (==3.4)
Requires-Dist: imageio (==2.33.0)
Requires-Dist: iopath (==0.1.10)
Requires-Dist: Jinja2 (==3.1.2)
Requires-Dist: kiwisolver (==1.4.5)
Requires-Dist: lazy-loader (==0.3)
Requires-Dist: llvmlite (==0.41.1)
Requires-Dist: MarkupSafe (==2.1.3)
Requires-Dist: matplotlib (==3.8.2)
Requires-Dist: mplcursors (==0.5.2)
Requires-Dist: mpmath (==1.3.0)
Requires-Dist: networkx (==3.0)
Requires-Dist: ninja (==1.11.1.1)
Requires-Dist: numba (==0.58.1)
Requires-Dist: numpy (==1.24.1)
Requires-Dist: opencv-python (==4.8.1.78)
Requires-Dist: opencv-python-headless (==4.8.1.78)
Requires-Dist: packaging (==23.2)
Requires-Dist: pandas (==2.1.4)
Requires-Dist: pdf2image (==1.16.3)
Requires-Dist: pdfminer.six (==20221105)
Requires-Dist: pdfplumber (==0.10.3)
Requires-Dist: Pillow (==10.1.0)
Requires-Dist: portalocker (==2.8.2)
Requires-Dist: pyclipper (==1.3.0.post5)
Requires-Dist: pycparser (==2.21)
Requires-Dist: pydantic (==2.5.2)
Requires-Dist: pydantic-core (==2.14.5)
Requires-Dist: PyMuPDF (==1.23.7)
Requires-Dist: PyMuPDFb (==1.23.7)
Requires-Dist: pyparsing (==3.1.1)
Requires-Dist: pypdfium2 (==4.24.0)
Requires-Dist: python-bidi (==0.4.2)
Requires-Dist: python-dateutil (==2.8.2)
Requires-Dist: python-multipart (==0.0.6)
Requires-Dist: pytz (==2023.3.post1)
Requires-Dist: pywin32 (==306)
Requires-Dist: PyYAML (==6.0.1)
Requires-Dist: requests (==2.28.1)
Requires-Dist: scikit-image (==0.22.0)
Requires-Dist: scipy (==1.11.4)
Requires-Dist: shapely (==2.0.2)
Requires-Dist: six (==1.16.0)
Requires-Dist: sniffio (==1.3.0)
Requires-Dist: starlette (==0.27.0)
Requires-Dist: sympy (==1.12)
Requires-Dist: tifffile (==2023.9.26)
Requires-Dist: torch (==2.1.1)
Requires-Dist: torchaudio (==2.1.1)
Requires-Dist: torchvision (==0.16.1)
Requires-Dist: tqdm (==4.66.1)
Requires-Dist: typing-extensions (==4.8.0)
Requires-Dist: tzdata (==2023.3)
Requires-Dist: urllib3 (==1.26.13)
Requires-Dist: uvicorn (==0.24.0.post1)
